yspacepy/__init__.py
yspacepy/api.py
yspacepy/objects/__init__.py
yspacepy-0.2.2.dist-info/LICENSE
yspacepy-0.2.2.dist-info/METADATA
yspacepy-0.2.2.dist-info/WHEEL
yspacepy-0.2.2.dist-info/top_level.txt
yspacepy-0.2.2.dist-info/RECORD
