Metadata-Version: 2.1
Name: yspacepy
Version: 0.2.2
Summary: http://y-space.pw companion package
Home-page: https://github.com/y-space/yspacepy
Author: Nuno Carvalho
Author-email: narcarvalho@gmail.com
License: MIT
Platform: UNKNOWN
Requires-Dist: astropy
